MANIFEST.in
README.rst
requirements.txt
setup.cfg
setup.py
kotti_lms_theme/__init__.py
kotti_lms_theme/__init__.pyc
kotti_lms_theme/fanstatic.py
kotti_lms_theme/fanstatic.pyc
kotti_lms_theme.egg-info/PKG-INFO
kotti_lms_theme.egg-info/SOURCES.txt
kotti_lms_theme.egg-info/dependency_links.txt
kotti_lms_theme.egg-info/entry_points.txt
kotti_lms_theme.egg-info/not-zip-safe
kotti_lms_theme.egg-info/requires.txt
kotti_lms_theme.egg-info/top_level.txt
kotti_lms_theme/alembic/script.py.mako
kotti_lms_theme/locale/.gitkeep
kotti_lms_theme/static/scripts.js
kotti_lms_theme/static/scripts.min.js
kotti_lms_theme/static/styles.css
kotti_lms_theme/static/styles.min.css
kotti_lms_theme/static/css/animate.css
kotti_lms_theme/static/css/bootstrap.min.css
kotti_lms_theme/static/css/sidebar.css
kotti_lms_theme/static/css/style.css
kotti_lms_theme/static/css/patterns/3.png
kotti_lms_theme/static/css/patterns/4.png
kotti_lms_theme/static/css/patterns/header-profile-skin-1.png
kotti_lms_theme/static/css/patterns/header-profile-skin-2.png
kotti_lms_theme/static/css/patterns/header-profile-skin-3.png
kotti_lms_theme/static/css/patterns/header-profile.png
kotti_lms_theme/static/css/patterns/shattered.png
kotti_lms_theme/static/css/plugins/awesome-bootstrap-checkbox/awesome-bootstrap-checkbox.css
kotti_lms_theme/static/css/plugins/blueimp/css/blueimp-gallery.min.css
kotti_lms_theme/static/css/plugins/blueimp/img/error.png
kotti_lms_theme/static/css/plugins/blueimp/img/error.svg
kotti_lms_theme/static/css/plugins/blueimp/img/loading.gif
kotti_lms_theme/static/css/plugins/blueimp/img/play-pause.png
kotti_lms_theme/static/css/plugins/blueimp/img/play-pause.svg
kotti_lms_theme/static/css/plugins/blueimp/img/video-play.png
kotti_lms_theme/static/css/plugins/blueimp/img/video-play.svg
kotti_lms_theme/static/css/plugins/bootstrap-markdown/bootstrap-markdown.min.css
kotti_lms_theme/static/css/plugins/bootstrapTour/bootstrap-tour.min.css
kotti_lms_theme/static/css/plugins/c3/c3.min.css
kotti_lms_theme/static/css/plugins/chartist/chartist.min.css
kotti_lms_theme/static/css/plugins/chosen/chosen-sprite.png
kotti_lms_theme/static/css/plugins/chosen/chosen-sprite@2x.png
kotti_lms_theme/static/css/plugins/chosen/chosen.css
